{"data":{"allContentfulContactPage":{"edges":[{"node":{"title":"Contactez-moi","subtitle":"Benoit Maigret | Développeur Front-End Freelance","content":{"content":"Vous souhaitez me contacter, discuter de votre projet ? Envoyez moi simplement un email à *hello\\[at\\]benoitmaigret.com* ou vous pouvez me trouver sur [Github](https://github.com/BenMt \"Github\"), [Twitter](https://twitter.com/benoitmaigret \"Twitter\") ou [LinkedIn](https://www.linkedin.com/in/benoitmaigret/ \"LinkedIn\")"},"location":"Mulhouse"}}]}}}